everypolitician_popolo-0.0.11.dist-info/DESCRIPTION.rst
everypolitician_popolo-0.0.11.dist-info/METADATA
everypolitician_popolo-0.0.11.dist-info/RECORD
everypolitician_popolo-0.0.11.dist-info/WHEEL
everypolitician_popolo-0.0.11.dist-info/metadata.json
everypolitician_popolo-0.0.11.dist-info/top_level.txt
popolo_data/__init__.py
popolo_data/base.py
popolo_data/importer.py
tests/__init__.py
tests/helpers.py
tests/test_area.py
tests/test_event.py
tests/test_load.py
tests/test_membership.py
tests/test_organization.py
tests/test_person.py
tests/test_post.py
tests/test_twitter.py
