Metadata-Version: 2.0
Name: everypolitician-popolo
Version: 0.0.11
Summary: Parse and model Popolo data from EveryPolitician
Home-page: UNKNOWN
Author: Mark Longair
Author-email: mark@mysociety.org
License: AGPL
Keywords: politics data civic-tech
Platform: UNKNOWN
Requires-Dist: approx-dates
Requires-Dist: requests
Requires-Dist: six (>=1.9.0)
